wires/__init__.py
wires/_callable.py
wires/_shared.py
wires/_wires.py
wires-19.2.0.dist-info/LICENSE
wires-19.2.0.dist-info/METADATA
wires-19.2.0.dist-info/WHEEL
wires-19.2.0.dist-info/top_level.txt
wires-19.2.0.dist-info/RECORD
